budgetguard/__init__.py
budgetguard/core/__init__.py
budgetguard/core/data_access_service/__init__.py
budgetguard/core/data_access_service/data_connections/__init__.py
budgetguard/core/data_access_service/data_connections/aws_connection.py
budgetguard/core/data_access_service/data_connections/connection.py
budgetguard/core/data_access_service/data_connections/exchange_rates_api_connection.py
budgetguard/core/data_access_service/data_connections/nordigen_connection.py
budgetguard/core/data_access_service/data_connections/s3_connection.py
budgetguard/core/data_access_service/data_connections/spark_s3_connection.py
budgetguard/core/data_access_service/data_loaders/__init__.py
budgetguard/core/data_access_service/data_loaders/data_loader.py
budgetguard/core/data_access_service/data_loaders/exchange_rates_data_loader.py
budgetguard/core/data_access_service/data_loaders/nordigen_data_loader.py
budgetguard/core/data_access_service/data_loaders/s3_data_loader.py
budgetguard/core/data_access_service/data_loaders/spark_s3_data_loader.py
budgetguard/core/datalake/__init__.py
budgetguard/core/datalake/budgetguard-datalake-table-definition-schema.json
budgetguard/core/datalake/datalake.py
budgetguard/core/datalake/layers/bronze/balances.yaml
budgetguard/core/datalake/layers/bronze/details.yaml
budgetguard/core/datalake/layers/bronze/metadata.yaml
budgetguard/core/datalake/layers/bronze/transactions.yaml
budgetguard/core/datalake/layers/gold/.gitkeep
budgetguard/core/datalake/layers/ingest/balances.yaml
budgetguard/core/datalake/layers/ingest/details.yaml
budgetguard/core/datalake/layers/ingest/metadata.yaml
budgetguard/core/datalake/layers/ingest/transactions.yaml
budgetguard/core/datalake/layers/master/exchange_rates.yaml
budgetguard/core/datalake/layers/silver/balances.yaml
budgetguard/core/datalake/layers/silver/details.yaml
budgetguard/core/datalake/layers/silver/metadata.yaml
budgetguard/core/datalake/layers/silver/transactions.yaml
budgetguard-0.42.2.dist-info/LICENSE
budgetguard-0.42.2.dist-info/METADATA
budgetguard-0.42.2.dist-info/WHEEL
budgetguard-0.42.2.dist-info/RECORD
