Metadata-Version: 2.1
Name: budgetguard
Version: 0.42.2
Summary: 
Author: Mateusz Borsuk
Author-email: mtszborsuk212@gmail.com
Requires-Python: >=3.8.1,<=3.11
Classifier: Programming Language :: Python :: 3
Classifier: Programming Language :: Python :: 3.9
Classifier: Programming Language :: Python :: 3.10
Classifier: Programming Language :: Python :: 3.11
Requires-Dist: aws-cdk-lib (>=2.91.0,<3.0.0)
Requires-Dist: boto3 (>=1.26.130,<2.0.0)
Requires-Dist: forex-python (>=1.8,<2.0)
Requires-Dist: loguru (>=0.7.0,<0.8.0)
Requires-Dist: nordigen (>=1.3.1,<2.0.0)
Requires-Dist: pyspark (==3.2.0)
Requires-Dist: python-dotenv (>=1.0.0,<2.0.0)
Requires-Dist: pyyaml (>=6.0.1,<7.0.0)
Requires-Dist: tqdm (>=4.66.1,<5.0.0)
